[
    {
        "SongID": 3,
        "Title": "LALA",
        "Artist": "Myke Towers",
        "Position": 49
    },
    {
        "SongID": 9,
        "Title": "LUNA",
        "Artist": "Feid",
        "Position": 6
    },
    {
        "SongID": 13,
        "Title": "La Diabla",
        "Artist": "Xavi",
        "Position": 142
    },
    {
        "SongID": 15,
        "Title": "PERRO NEGRO",
        "Artist": "Bad Bunny",
        "Position": 28
    },
    {
        "SongID": 19,
        "Title": "Columbia",
        "Artist": "Quevedo",
        "Position": 27
    },
    {
        "SongID": 25,
        "Title": "Love Me Again",
        "Artist": "V",
        "Position": 5
    },
    {
        "SongID": 32,
        "Title": "Classy 101",
        "Artist": "Feid",
        "Position": 47
    },
    {
        "SongID": 72,
        "Title": "DILUVIO",
        "Artist": "Rauw Alejandro",
        "Position": 75
    },
    {
        "SongID": 77,
        "Title": "Una Foto Remix",
        "Artist": "Mesita",
        "Position": 43
    },
    {
        "SongID": 92,
        "Title": "AMARGURA",
        "Artist": "KAROL G",
        "Position": 35
    },
    {
        "SongID": 118,
        "Title": "Me Porto Bonito",
        "Artist": "Bad Bunny",
        "Position": 169
    },
    {
        "SongID": 134,
        "Title": "Primera Cita",
        "Artist": "Carin Leon",
        "Position": 64
    },
    {
        "SongID": 136,
        "Title": "Los del Espacio",
        "Artist": "LIT killah",
        "Position": 182
    },
    {
        "SongID": 139,
        "Title": "El Merengue",
        "Artist": "Marshmello",
        "Position": 109
    },
    {
        "SongID": 147,
        "Title": "LA FALDA",
        "Artist": "Myke Towers",
        "Position": 25
    },
    {
        "SongID": 168,
        "Title": "Ojitos Lindos",
        "Artist": "Bad Bunny",
        "Position": 96
    },
    {
        "SongID": 173,
        "Title": "Que Vuelvas",
        "Artist": "Carin Leon",
        "Position": 76
    },
    {
        "SongID": 249,
        "Title": "La Bachata",
        "Artist": "Manuel Turizo",
        "Position": 42
    },
    {
        "SongID": 265,
        "Title": "CORAZÓN VACÍO",
        "Artist": "Maria Becerra",
        "Position": 146
    },
    {
        "SongID": 357,
        "Title": "Un Finde | CROSSOVER #2",
        "Artist": "Big One",
        "Position": 40
    },
    {
        "SongID": 358,
        "Title": "Rara Vez",
        "Artist": "Taiu",
        "Position": 44
    },
    {
        "SongID": 359,
        "Title": "LA INOCENTE",
        "Artist": "Mora",
        "Position": 130
    },
    {
        "SongID": 450,
        "Title": "Moscow Mule",
        "Artist": "Bad Bunny",
        "Position": 131
    },
    {
        "SongID": 481,
        "Title": "Feliz Cumpleaños Ferxxo",
        "Artist": "Feid",
        "Position": 31
    },
    {
        "SongID": 519,
        "Title": "ALV",
        "Artist": "Arcángel",
        "Position": 155
    },
    {
        "SongID": 572,
        "Title": "La Curiosidad",
        "Artist": "Jay Wheeler",
        "Position": 81
    },
    {
        "SongID": 603,
        "Title": "PROVENZA",
        "Artist": "KAROL G",
        "Position": 100
    },
    {
        "SongID": 638,
        "Title": "Es un Secreto",
        "Artist": "Plan B",
        "Position": 11
    },
    {
        "SongID": 825,
        "Title": "Ni Una Ni Dos",
        "Artist": "BM",
        "Position": 173
    },
    {
        "SongID": 829,
        "Title": "PUNTO G",
        "Artist": "Quevedo",
        "Position": 181
    },
    {
        "SongID": 834,
        "Title": "Normal",
        "Artist": "Feid",
        "Position": 37
    },
    {
        "SongID": 836,
        "Title": "Dile",
        "Artist": "Don Omar",
        "Position": 144
    },
    {
        "SongID": 892,
        "Title": "No Se Va - En Vivo",
        "Artist": "Grupo Frontera",
        "Position": 129
    },
    {
        "SongID": 1068,
        "Title": "OJITOS ROJOS",
        "Artist": "Grupo Frontera",
        "Position": 18
    },
    {
        "SongID": 1069,
        "Title": "Pobre Corazón - En Vivo",
        "Artist": "Ke Personajes",
        "Position": 89
    },
    {
        "SongID": 1072,
        "Title": "Me Rehúso",
        "Artist": "Danny Ocean",
        "Position": 65
    },
    {
        "SongID": 1081,
        "Title": "Amanece",
        "Artist": "Anuel AA",
        "Position": 33
    },
    {
        "SongID": 1100,
        "Title": "Si Estuviésemos Juntos",
        "Artist": "Bad Bunny",
        "Position": 103
    },
    {
        "SongID": 1162,
        "Title": "OA",
        "Artist": "Anuel AA",
        "Position": 156
    },
    {
        "SongID": 1181,
        "Title": "M.A.I",
        "Artist": "Milo j",
        "Position": 97
    },
    {
        "SongID": 1183,
        "Title": "Ya No Vuelvas (Versión Cuarteto)",
        "Artist": "Luck Ra",
        "Position": 113
    },
    {
        "SongID": 1255,
        "Title": "No Se Va",
        "Artist": "Morat",
        "Position": 188
    },
    {
        "SongID": 1328,
        "Title": "Diles",
        "Artist": "Bad Bunny",
        "Position": 133
    },
    {
        "SongID": 1330,
        "Title": "Pa Ti Estoy",
        "Artist": "Ozuna",
        "Position": 82
    },
    {
        "SongID": 1344,
        "Title": "Rosas",
        "Artist": "La Oreja de Van Gogh",
        "Position": 78
    },
    {
        "SongID": 1345,
        "Title": "Me Voy",
        "Artist": "Julieta Venegas",
        "Position": 70
    },
    {
        "SongID": 1421,
        "Title": "Tiroteo - Remix",
        "Artist": "Marc Seguí",
        "Position": 157
    },
    {
        "SongID": 1557,
        "Title": "HOLA PERDIDA",
        "Artist": "Luck Ra",
        "Position": 77
    },
    {
        "SongID": 1581,
        "Title": "Propuesta Indecente",
        "Artist": "Romeo Santos",
        "Position": 122
    },
    {
        "SongID": 1727,
        "Title": "Besos En Guerra",
        "Artist": "Morat",
        "Position": 200
    },
    {
        "SongID": 1824,
        "Title": "La Morocha",
        "Artist": "Luck Ra",
        "Position": 59
    },
    {
        "SongID": 1852,
        "Title": "VISTA AL MAR",
        "Artist": "Quevedo",
        "Position": 86
    },
    {
        "SongID": 1919,
        "Title": "Déjala Que Vuelva",
        "Artist": "Piso 21",
        "Position": 66
    },
    {
        "SongID": 1974,
        "Title": "Eres Mía",
        "Artist": "Romeo Santos",
        "Position": 193
    },
    {
        "SongID": 2102,
        "Title": "Fuera del mercado",
        "Artist": "Danny Ocean",
        "Position": 183
    },
    {
        "SongID": 2105,
        "Title": "Te Vi",
        "Artist": "Piso 21",
        "Position": 114
    },
    {
        "SongID": 2171,
        "Title": "Mientes",
        "Artist": "Camila",
        "Position": 178
    },
    {
        "SongID": 2269,
        "Title": "El Amor De Mi Vida",
        "Artist": "Los Ángeles Azules",
        "Position": 73
    },
    {
        "SongID": 2273,
        "Title": "Ferxxo 100",
        "Artist": "Feid",
        "Position": 152
    },
    {
        "SongID": 2321,
        "Title": "Dia de Enero",
        "Artist": "Shakira",
        "Position": 164
    },
    {
        "SongID": 2368,
        "Title": "Si No Le Contesto",
        "Artist": "Plan B",
        "Position": 149
    },
    {
        "SongID": 2386,
        "Title": "Sola (Remix)",
        "Artist": "Anuel AA",
        "Position": 51
    },
    {
        "SongID": 2543,
        "Title": "Tal Vez",
        "Artist": "Paulo Londra",
        "Position": 184
    },
    {
        "SongID": 2617,
        "Title": "Solos",
        "Artist": "Tony Dize",
        "Position": 161
    },
    {
        "SongID": 2642,
        "Title": "Todo De Ti",
        "Artist": "Rauw Alejandro",
        "Position": 177
    },
    {
        "SongID": 2705,
        "Title": "Your Love",
        "Artist": "The Outfield",
        "Position": 186
    },
    {
        "SongID": 2769,
        "Title": "Borro Cassette",
        "Artist": "Maluma",
        "Position": 32
    },
    {
        "SongID": 2828,
        "Title": "Por Que Te Demoras?",
        "Artist": "Plan B",
        "Position": 167
    },
    {
        "SongID": 3037,
        "Title": "Te Amo",
        "Artist": "Piso 21",
        "Position": 88
    },
    {
        "SongID": 3060,
        "Title": "Puntos Suspensivos",
        "Artist": "Piso 21",
        "Position": 119
    },
    {
        "SongID": 3098,
        "Title": "No Te Hagas",
        "Artist": "Jory Boy",
        "Position": 148
    },
    {
        "SongID": 3136,
        "Title": "La Muralla Verde",
        "Artist": "Los Enanitos Verdes",
        "Position": 162
    },
    {
        "SongID": 3240,
        "Title": "COSAS QUE NO TE DIJE",
        "Artist": "SAIKO",
        "Position": 143
    },
    {
        "SongID": 3653,
        "Title": "Dile a El",
        "Artist": "Rauw Alejandro",
        "Position": 174
    },
    {
        "SongID": 3837,
        "Title": "Mamichula - con Nicki Nicole",
        "Artist": "Trueno",
        "Position": 192
    },
    {
        "SongID": 3864,
        "Title": "Tu Príncipe",
        "Artist": "Daddy Yankee",
        "Position": 180
    },
    {
        "SongID": 3904,
        "Title": "She Don't Give a Fo",
        "Artist": "Duki",
        "Position": 151
    },
    {
        "SongID": 4019,
        "Title": "Flaca",
        "Artist": "Andrés Calamaro",
        "Position": 135
    },
    {
        "SongID": 4066,
        "Title": "Hace Mucho Tiempo",
        "Artist": "Arcángel",
        "Position": 41
    },
    {
        "SongID": 4301,
        "Title": "Loca",
        "Artist": "KHEA",
        "Position": 123
    },
    {
        "SongID": 4490,
        "Title": "La Despedida",
        "Artist": "Daddy Yankee",
        "Position": 197
    },
    {
        "SongID": 5617,
        "Title": "Por Mil Noches",
        "Artist": "Airbag",
        "Position": 191
    },
    {
        "SongID": 5941,
        "Title": "Candy",
        "Artist": "Plan B",
        "Position": 101
    },
    {
        "SongID": 6312,
        "Title": "A las Nueve",
        "Artist": "No Te Va Gustar",
        "Position": 87
    },
    {
        "SongID": 6549,
        "Title": "FLECHAZO EN EL CENTRO",
        "Artist": "YSY A",
        "Position": 80
    },
    {
        "SongID": 7644,
        "Title": "Otra Noche",
        "Artist": "Los Ángeles Azules",
        "Position": 160
    },
    {
        "SongID": 8387,
        "Title": "Amanecemos",
        "Artist": "La Joaqui",
        "Position": 153
    },
    {
        "SongID": 9836,
        "Title": "Piel",
        "Artist": "Tiago PZK",
        "Position": 2
    },
    {
        "SongID": 12447,
        "Title": "Espresso",
        "Artist": "Sabrina Carpenter",
        "Position": 196
    },
    {
        "SongID": 12451,
        "Title": "BIRDS OF A FEATHER",
        "Artist": "Billie Eilish",
        "Position": 95
    },
    {
        "SongID": 12995,
        "Title": "Santa",
        "Artist": "Rvssian",
        "Position": 14
    },
    {
        "SongID": 13634,
        "Title": "MTG QUEM NÃO QUER SOU EU",
        "Artist": "DJ TOPO",
        "Position": 92
    },
    {
        "SongID": 13700,
        "Title": "DE LUNES A LUNES",
        "Artist": "Grupo Frontera",
        "Position": 115
    },
    {
        "SongID": 14882,
        "Title": "ADIVINO",
        "Artist": "Myke Towers",
        "Position": 84
    },
    {
        "SongID": 15611,
        "Title": "Perdonarte, ¿Para Qué?",
        "Artist": "Los Ángeles Azules",
        "Position": 21
    },
    {
        "SongID": 15825,
        "Title": "BESAME",
        "Artist": "Bhavi",
        "Position": 91
    },
    {
        "SongID": 16112,
        "Title": "HOY",
        "Artist": "The La Planta",
        "Position": 159
    },
    {
        "SongID": 16113,
        "Title": "30 GRADOS",
        "Artist": "El Turko",
        "Position": 62
    },
    {
        "SongID": 16115,
        "Title": "APAGA EL CEL",
        "Artist": "FloyyMenor",
        "Position": 165
    },
    {
        "SongID": 16116,
        "Title": "offline",
        "Artist": "Young Miko",
        "Position": 69
    },
    {
        "SongID": 16118,
        "Title": "BBY BOO - REMIX",
        "Artist": "iZaak",
        "Position": 26
    },
    {
        "SongID": 16126,
        "Title": "SI NO ES CONTIGO",
        "Artist": "Cris Mj",
        "Position": 29
    },
    {
        "SongID": 16256,
        "Title": "REAL GANGSTA LOVE",
        "Artist": "Trueno",
        "Position": 16
    },
    {
        "SongID": 16593,
        "Title": "Sin Ti No Sé Vivir",
        "Artist": "Los Ángeles Azules",
        "Position": 117
    },
    {
        "SongID": 18862,
        "Title": "POR QUÉ SERÁ",
        "Artist": "Grupo Frontera",
        "Position": 67
    },
    {
        "SongID": 18863,
        "Title": "EL AMOR DE SU VIDA",
        "Artist": "Grupo Frontera",
        "Position": 71
    },
    {
        "SongID": 19036,
        "Title": "QLONA",
        "Artist": "KAROL G",
        "Position": 22
    },
    {
        "SongID": 19074,
        "Title": "LA CANCIÓN",
        "Artist": "J Balvin",
        "Position": 50
    },
    {
        "SongID": 19678,
        "Title": "un x100to",
        "Artist": "Grupo Frontera",
        "Position": 36
    },
    {
        "SongID": 19687,
        "Title": "MI EX TENÍA RAZÓN",
        "Artist": "KAROL G",
        "Position": 24
    },
    {
        "SongID": 20327,
        "Title": "Miénteme",
        "Artist": "TINI",
        "Position": 111
    },
    {
        "SongID": 23665,
        "Title": "Maquillaje",
        "Artist": "Renn",
        "Position": 176
    },
    {
        "SongID": 23762,
        "Title": "Mirame",
        "Artist": "Blessd",
        "Position": 8
    },
    {
        "SongID": 24957,
        "Title": "Señal De Vida",
        "Artist": "Ñejo & Dalmata",
        "Position": 147
    },
    {
        "SongID": 24963,
        "Title": "WYA",
        "Artist": "J Abdiel",
        "Position": 85
    },
    {
        "SongID": 24965,
        "Title": "WYA REMIX RED",
        "Artist": "J Abdiel",
        "Position": 12
    },
    {
        "SongID": 33277,
        "Title": "FRI(END)S",
        "Artist": "V",
        "Position": 19
    },
    {
        "SongID": 33549,
        "Title": "Permitame",
        "Artist": "Tony Dize",
        "Position": 68
    },
    {
        "SongID": 118760,
        "Title": "Quiéreme Mientras Se Pueda",
        "Artist": "Manuel Turizo",
        "Position": 83
    },
    {
        "SongID": 118822,
        "Title": "PERO TÚ",
        "Artist": "KAROL G",
        "Position": 175
    },
    {
        "SongID": 118856,
        "Title": "Fanática Sensual",
        "Artist": "Plan B",
        "Position": 121
    },
    {
        "SongID": 120348,
        "Title": "Loco",
        "Artist": "Beéle",
        "Position": 72
    },
    {
        "SongID": 120351,
        "Title": "Nena Maldición",
        "Artist": "Paulo Londra",
        "Position": 137
    },
    {
        "SongID": 121425,
        "Title": "Me Vas a Extrañar",
        "Artist": "Japiaguar",
        "Position": 171
    },
    {
        "SongID": 121442,
        "Title": "Perdóname",
        "Artist": "La Factoria",
        "Position": 104
    },
    {
        "SongID": 122981,
        "Title": "Quevedo: Bzrp Music Sessions, Vol. 52",
        "Artist": "Bizarrap",
        "Position": 158
    },
    {
        "SongID": 122988,
        "Title": "Madura",
        "Artist": "Cosculluela",
        "Position": 39
    },
    {
        "SongID": 123006,
        "Title": "Te Busco",
        "Artist": "Cosculluela",
        "Position": 132
    },
    {
        "SongID": 123015,
        "Title": "MOJABI GHOST",
        "Artist": "Tainy",
        "Position": 189
    },
    {
        "SongID": 124437,
        "Title": "Yo Quisiera",
        "Artist": "Reik",
        "Position": 194
    },
    {
        "SongID": 127052,
        "Title": "Piensa En Mí",
        "Artist": "Grupo Mojado",
        "Position": 138
    },
    {
        "SongID": 178922,
        "Title": "Dulcemente Enamorada",
        "Artist": "Los Mier",
        "Position": 93
    },
    {
        "SongID": 178923,
        "Title": "Amor Platonico",
        "Artist": "Los Verduleros",
        "Position": 108
    },
    {
        "SongID": 178925,
        "Title": "Tomame O Dejame",
        "Artist": "Tropical Caribe",
        "Position": 56
    },
    {
        "SongID": 178928,
        "Title": "Me Ilusione",
        "Artist": "Binomio de Oro de América",
        "Position": 198
    },
    {
        "SongID": 178934,
        "Title": "Te Voy Amar",
        "Artist": "Jorge Acosta",
        "Position": 54
    },
    {
        "SongID": 178941,
        "Title": "Ahora Estoy Solo",
        "Artist": "Lalo Y Los Descalzos",
        "Position": 79
    },
    {
        "SongID": 178942,
        "Title": "Quien Diria",
        "Artist": "Tropical Florida",
        "Position": 187
    },
    {
        "SongID": 178944,
        "Title": "Me Estas Volviendo Loco",
        "Artist": "Cumbia Juan",
        "Position": 199
    },
    {
        "SongID": 178954,
        "Title": "Ay Que Vida",
        "Artist": "Qmbia Juan",
        "Position": 106
    },
    {
        "SongID": 178969,
        "Title": "Siempre Me Buscabas",
        "Artist": "Lalo Y Los Descalzos",
        "Position": 52
    },
    {
        "SongID": 179004,
        "Title": "Anoche",
        "Artist": "Lalo Y Los Descalzos",
        "Position": 58
    },
    {
        "SongID": 179013,
        "Title": "Como Duele Amar",
        "Artist": "Grupo Azteka",
        "Position": 105
    },
    {
        "SongID": 179036,
        "Title": "Tal Vez Seas Tu",
        "Artist": "Grupo Azteka",
        "Position": 140
    },
    {
        "SongID": 198093,
        "Title": "La Bebe - Remix",
        "Artist": "Yng Lvcas",
        "Position": 102
    },
    {
        "SongID": 198095,
        "Title": "TQG",
        "Artist": "KAROL G",
        "Position": 172
    },
    {
        "SongID": 198143,
        "Title": "Toda - Remix",
        "Artist": "Alex Rose",
        "Position": 134
    },
    {
        "SongID": 200196,
        "Title": "Persia - Remix",
        "Artist": "Jossef",
        "Position": 154
    },
    {
        "SongID": 200222,
        "Title": "Hoy",
        "Artist": "Valentino Merlo",
        "Position": 9
    },
    {
        "SongID": 245449,
        "Title": "Me Extrañarás",
        "Artist": "Noa - Noa",
        "Position": 128
    },
    {
        "SongID": 245456,
        "Title": "Necesito De Ti",
        "Artist": "Grupo Azteka",
        "Position": 99
    },
    {
        "SongID": 245467,
        "Title": "Tu No Sabes Nada",
        "Artist": "Jorge Acosta",
        "Position": 168
    },
    {
        "SongID": 245481,
        "Title": "Pera Madura (Remastered 2023)",
        "Artist": "Lalo Y Los Descalzos",
        "Position": 166
    },
    {
        "SongID": 245488,
        "Title": "Mary Es Mi Amor",
        "Artist": "Grupo Azteka",
        "Position": 185
    },
    {
        "SongID": 245501,
        "Title": "De Pronto Llegó el Amor",
        "Artist": "Jorge Acosta",
        "Position": 163
    },
    {
        "SongID": 501280,
        "Title": "Die With A Smile",
        "Artist": "Lady Gaga",
        "Position": 38
    },
    {
        "SongID": 501283,
        "Title": "Who",
        "Artist": "Jimin",
        "Position": 4
    },
    {
        "SongID": 501286,
        "Title": "Si Antes Te Hubiera Conocido",
        "Artist": "KAROL G",
        "Position": 3
    },
    {
        "SongID": 501299,
        "Title": "Gata Only",
        "Artist": "FloyyMenor",
        "Position": 46
    },
    {
        "SongID": 501305,
        "Title": "UWAIE",
        "Artist": "Kapo",
        "Position": 7
    },
    {
        "SongID": 501365,
        "Title": "Ohnana",
        "Artist": "Kapo",
        "Position": 13
    },
    {
        "SongID": 501371,
        "Title": "PELIGROSA",
        "Artist": "FloyyMenor",
        "Position": 10
    },
    {
        "SongID": 501375,
        "Title": "Orion",
        "Artist": "Boza",
        "Position": 118
    },
    {
        "SongID": 501386,
        "Title": "Tengo Un Plan - Remix",
        "Artist": "Key-Key",
        "Position": 136
    },
    {
        "SongID": 501387,
        "Title": "No Ponga Excusas",
        "Artist": "Cris Mj",
        "Position": 94
    },
    {
        "SongID": 501388,
        "Title": "Cuando Te Vi | CROSSOVER #5",
        "Artist": "Big One",
        "Position": 90
    },
    {
        "SongID": 501401,
        "Title": "HOLA PERDIDA REMIX",
        "Artist": "Luck Ra",
        "Position": 179
    },
    {
        "SongID": 501406,
        "Title": "Alegría",
        "Artist": "Tiago PZK",
        "Position": 53
    },
    {
        "SongID": 501408,
        "Title": "UN SIGLO SIN TI",
        "Artist": "Luck Ra",
        "Position": 112
    },
    {
        "SongID": 501422,
        "Title": "SAN TURRONA",
        "Artist": "La Joaqui",
        "Position": 190
    },
    {
        "SongID": 501424,
        "Title": "3 PECADOS DESPUES…",
        "Artist": "Milo j",
        "Position": 74
    },
    {
        "SongID": 501431,
        "Title": "Si Un Día Estás Sola | CROSSOVER #7",
        "Artist": "Big One",
        "Position": 170
    },
    {
        "SongID": 501441,
        "Title": "SE ME OLVIDA",
        "Artist": "Maisak",
        "Position": 20
    },
    {
        "SongID": 501503,
        "Title": "Si No Quieres No",
        "Artist": "Luis R Conriquez",
        "Position": 98
    },
    {
        "SongID": 501508,
        "Title": "Según Quién",
        "Artist": "Maluma",
        "Position": 15
    },
    {
        "SongID": 501510,
        "Title": "Que Onda",
        "Artist": "Calle 24",
        "Position": 120
    },
    {
        "SongID": 501515,
        "Title": "SORRY 4 THAT MUCH",
        "Artist": "Feid",
        "Position": 57
    },
    {
        "SongID": 501540,
        "Title": "ÁNGEL",
        "Artist": "Grupo Frontera",
        "Position": 139
    },
    {
        "SongID": 501561,
        "Title": "Só Fé",
        "Artist": "Grelo",
        "Position": 17
    },
    {
        "SongID": 501565,
        "Title": "De Graça ou Pagando",
        "Artist": "Grelo",
        "Position": 63
    },
    {
        "SongID": 501649,
        "Title": "Hasta Aquí Llegué",
        "Artist": "Nanpa Básico",
        "Position": 125
    },
    {
        "SongID": 501675,
        "Title": "Desesperados",
        "Artist": "Rauw Alejandro",
        "Position": 55
    },
    {
        "SongID": 501813,
        "Title": "TAMBIÉN",
        "Artist": "Myke Towers",
        "Position": 110
    },
    {
        "SongID": 502606,
        "Title": "Partido en Dos",
        "Artist": "Banda Tava'i Oficial",
        "Position": 45
    },
    {
        "SongID": 502819,
        "Title": "Kyoto",
        "Artist": "Omar Courtz",
        "Position": 34
    },
    {
        "SongID": 503708,
        "Title": "AGORA",
        "Artist": "Maria Becerra",
        "Position": 60
    },
    {
        "SongID": 503723,
        "Title": "Princesa",
        "Artist": "Paulo Londra",
        "Position": 126
    },
    {
        "SongID": 503735,
        "Title": "Después De La 1",
        "Artist": "Cris Mj",
        "Position": 30
    },
    {
        "SongID": 503926,
        "Title": "Hablame Claro",
        "Artist": "Yandel",
        "Position": 107
    },
    {
        "SongID": 503967,
        "Title": "Hey Mor",
        "Artist": "Ozuna",
        "Position": 127
    },
    {
        "SongID": 530419,
        "Title": "Q U E V A S H A C E R H O Y ?",
        "Artist": "Omar Courtz",
        "Position": 1
    },
    {
        "SongID": 531611,
        "Title": "SERIO CON ESE Q",
        "Artist": "Omar Courtz",
        "Position": 141
    },
    {
        "SongID": 532040,
        "Title": "Call Center",
        "Artist": "Smash Hits",
        "Position": 150
    },
    {
        "SongID": 538723,
        "Title": "Soltera",
        "Artist": "Shakira",
        "Position": 23
    },
    {
        "SongID": 538799,
        "Title": "Vai Lá - Ao Vivo em Goiânia",
        "Artist": "Maiara & Maraisa",
        "Position": 48
    },
    {
        "SongID": 538834,
        "Title": "Menina do Paraguay",
        "Artist": "Mc Leléto",
        "Position": 61
    },
    {
        "SongID": 538844,
        "Title": "Deuño De Ti",
        "Artist": "Lalo Y Los Descalzos",
        "Position": 124
    },
    {
        "SongID": 538904,
        "Title": "KINTSUGI",
        "Artist": "HUMBE",
        "Position": 116
    },
    {
        "SongID": 538907,
        "Title": "Te Quiero Asi",
        "Artist": "Lalo Y Los Descalzos",
        "Position": 145
    },
    {
        "SongID": 539123,
        "Title": "Atento al Lobo",
        "Artist": "Jorge Acosta",
        "Position": 195
    }
]