[
    {
        "SongID": 1,
        "Title": "Cruel Summer",
        "Artist": "Taylor Swift",
        "Position": 196
    },
    {
        "SongID": 6,
        "Title": "One Of The Girls",
        "Artist": "The Weeknd",
        "Position": 27
    },
    {
        "SongID": 7,
        "Title": "What Was I Made For? [From The Motion Picture \"Barbie\"]",
        "Artist": "Billie Eilish",
        "Position": 173
    },
    {
        "SongID": 8,
        "Title": "Standing Next to You",
        "Artist": "Jung Kook",
        "Position": 76
    },
    {
        "SongID": 16,
        "Title": "Popular",
        "Artist": "The Weeknd",
        "Position": 127
    },
    {
        "SongID": 18,
        "Title": "fukumean",
        "Artist": "Gunna",
        "Position": 161
    },
    {
        "SongID": 25,
        "Title": "Love Me Again",
        "Artist": "V",
        "Position": 28
    },
    {
        "SongID": 37,
        "Title": "I Wanna Be Yours",
        "Artist": "Arctic Monkeys",
        "Position": 23
    },
    {
        "SongID": 46,
        "Title": "FE!N",
        "Artist": "Travis Scott",
        "Position": 21
    },
    {
        "SongID": 51,
        "Title": "As It Was",
        "Artist": "Harry Styles",
        "Position": 190
    },
    {
        "SongID": 53,
        "Title": "Kill Bill",
        "Artist": "SZA",
        "Position": 46
    },
    {
        "SongID": 64,
        "Title": "Sweater Weather",
        "Artist": "The Neighbourhood",
        "Position": 14
    },
    {
        "SongID": 76,
        "Title": "Shut up My Moms Calling",
        "Artist": "Hotel Ugly",
        "Position": 126
    },
    {
        "SongID": 97,
        "Title": "Another Love",
        "Artist": "Tom Odell",
        "Position": 65
    },
    {
        "SongID": 99,
        "Title": "Mockingbird",
        "Artist": "Eminem",
        "Position": 91
    },
    {
        "SongID": 101,
        "Title": "My Love Mine All Mine",
        "Artist": "Mitski",
        "Position": 33
    },
    {
        "SongID": 103,
        "Title": "Pink + White",
        "Artist": "Frank Ocean",
        "Position": 185
    },
    {
        "SongID": 111,
        "Title": "Not Allowed",
        "Artist": "TV Girl",
        "Position": 61
    },
    {
        "SongID": 121,
        "Title": "Romantic Homicide",
        "Artist": "d4vd",
        "Position": 81
    },
    {
        "SongID": 125,
        "Title": "Say Yes To Heaven",
        "Artist": "Lana Del Rey",
        "Position": 120
    },
    {
        "SongID": 142,
        "Title": "Without Me",
        "Artist": "Eminem",
        "Position": 141
    },
    {
        "SongID": 152,
        "Title": "Night Changes",
        "Artist": "One Direction",
        "Position": 144
    },
    {
        "SongID": 170,
        "Title": "Under The Influence",
        "Artist": "Chris Brown",
        "Position": 194
    },
    {
        "SongID": 171,
        "Title": "Too Many Nights",
        "Artist": "Metro Boomin",
        "Position": 148
    },
    {
        "SongID": 174,
        "Title": "The Color Violet",
        "Artist": "Tory Lanez",
        "Position": 92
    },
    {
        "SongID": 196,
        "Title": "Dandelions",
        "Artist": "Ruth B.",
        "Position": 183
    },
    {
        "SongID": 201,
        "Title": "Viva La Vida",
        "Artist": "Coldplay",
        "Position": 100
    },
    {
        "SongID": 202,
        "Title": "Heartless",
        "Artist": "Kanye West",
        "Position": 162
    },
    {
        "SongID": 204,
        "Title": "we fell in love in october",
        "Artist": "girl in red",
        "Position": 16
    },
    {
        "SongID": 205,
        "Title": "Apocalypse",
        "Artist": "Cigarettes After Sex",
        "Position": 19
    },
    {
        "SongID": 206,
        "Title": "Lovers Rock",
        "Artist": "TV Girl",
        "Position": 98
    },
    {
        "SongID": 214,
        "Title": "Softcore",
        "Artist": "The Neighbourhood",
        "Position": 47
    },
    {
        "SongID": 215,
        "Title": "Daddy Issues",
        "Artist": "The Neighbourhood",
        "Position": 88
    },
    {
        "SongID": 232,
        "Title": "Let Me Down Slowly",
        "Artist": "Alec Benjamin",
        "Position": 195
    },
    {
        "SongID": 243,
        "Title": "Cigarettes out the Window",
        "Artist": "TV Girl",
        "Position": 90
    },
    {
        "SongID": 245,
        "Title": "I Love You So",
        "Artist": "The Walters",
        "Position": 87
    },
    {
        "SongID": 250,
        "Title": "Dark Red",
        "Artist": "Steve Lacy",
        "Position": 150
    },
    {
        "SongID": 272,
        "Title": "From The Start",
        "Artist": "Laufey",
        "Position": 136
    },
    {
        "SongID": 277,
        "Title": "Somewhere Only We Know",
        "Artist": "Keane",
        "Position": 177
    },
    {
        "SongID": 280,
        "Title": "505",
        "Artist": "Arctic Monkeys",
        "Position": 79
    },
    {
        "SongID": 288,
        "Title": "Cry",
        "Artist": "Cigarettes After Sex",
        "Position": 34
    },
    {
        "SongID": 289,
        "Title": "K.",
        "Artist": "Cigarettes After Sex",
        "Position": 60
    },
    {
        "SongID": 290,
        "Title": "Sunsetz",
        "Artist": "Cigarettes After Sex",
        "Position": 62
    },
    {
        "SongID": 301,
        "Title": "The Night We Met",
        "Artist": "Lord Huron",
        "Position": 53
    },
    {
        "SongID": 303,
        "Title": "Revenge",
        "Artist": "XXXTENTACION",
        "Position": 37
    },
    {
        "SongID": 318,
        "Title": "Summertime Sadness",
        "Artist": "Lana Del Rey",
        "Position": 56
    },
    {
        "SongID": 319,
        "Title": "Freaks",
        "Artist": "Surf Curse",
        "Position": 167
    },
    {
        "SongID": 329,
        "Title": "Montagem Mysterious Game",
        "Artist": "LXNGVX",
        "Position": 80
    },
    {
        "SongID": 388,
        "Title": "Reflections",
        "Artist": "The Neighbourhood",
        "Position": 72
    },
    {
        "SongID": 407,
        "Title": "Shameless",
        "Artist": "Camila Cabello",
        "Position": 130
    },
    {
        "SongID": 500,
        "Title": "Bring Me To Life",
        "Artist": "Evanescence",
        "Position": 197
    },
    {
        "SongID": 521,
        "Title": "You Get Me So High",
        "Artist": "The Neighbourhood",
        "Position": 172
    },
    {
        "SongID": 576,
        "Title": "Ransom",
        "Artist": "Lil Tecca",
        "Position": 101
    },
    {
        "SongID": 577,
        "Title": "We Don't Talk Anymore",
        "Artist": "Charlie Puth",
        "Position": 49
    },
    {
        "SongID": 700,
        "Title": "Sweet",
        "Artist": "Cigarettes After Sex",
        "Position": 165
    },
    {
        "SongID": 726,
        "Title": "ocean eyes",
        "Artist": "Billie Eilish",
        "Position": 176
    },
    {
        "SongID": 734,
        "Title": "HIGHEST IN THE ROOM",
        "Artist": "Travis Scott",
        "Position": 64
    },
    {
        "SongID": 813,
        "Title": "Friends",
        "Artist": "Chase Atlantic",
        "Position": 174
    },
    {
        "SongID": 867,
        "Title": "Set Fire to the Rain",
        "Artist": "Adele",
        "Position": 40
    },
    {
        "SongID": 1151,
        "Title": "Rolling in the Deep",
        "Artist": "Adele",
        "Position": 117
    },
    {
        "SongID": 1154,
        "Title": "3D",
        "Artist": "Jung Kook",
        "Position": 99
    },
    {
        "SongID": 1170,
        "Title": "I Smoked Away My Brain (I'm God x Demons Mashup)",
        "Artist": "A$AP Rocky",
        "Position": 179
    },
    {
        "SongID": 1173,
        "Title": "Fuck Love",
        "Artist": "XXXTENTACION",
        "Position": 129
    },
    {
        "SongID": 1302,
        "Title": "i'm yours",
        "Artist": "Isabel LaRosa",
        "Position": 125
    },
    {
        "SongID": 1450,
        "Title": "Sex, Drugs, Etc.",
        "Artist": "Beach Weather",
        "Position": 135
    },
    {
        "SongID": 1555,
        "Title": "Heavenly",
        "Artist": "Cigarettes After Sex",
        "Position": 110
    },
    {
        "SongID": 1725,
        "Title": "Impossible",
        "Artist": "James Arthur",
        "Position": 193
    },
    {
        "SongID": 2148,
        "Title": "Diet Mountain Dew",
        "Artist": "Lana Del Rey",
        "Position": 157
    },
    {
        "SongID": 2264,
        "Title": "greedy",
        "Artist": "Tate McRae",
        "Position": 187
    },
    {
        "SongID": 3005,
        "Title": "الك الك گلبي يحن",
        "Artist": "سجاد حقي",
        "Position": 12
    },
    {
        "SongID": 3901,
        "Title": "Love In The Dark",
        "Artist": "Adele",
        "Position": 186
    },
    {
        "SongID": 3966,
        "Title": "Judas",
        "Artist": "Lady Gaga",
        "Position": 54
    },
    {
        "SongID": 4402,
        "Title": "Bye Bye Bye",
        "Artist": "*NSYNC",
        "Position": 58
    },
    {
        "SongID": 5068,
        "Title": "Forever Young",
        "Artist": "Alphaville",
        "Position": 102
    },
    {
        "SongID": 6122,
        "Title": "Candy",
        "Artist": "Doja Cat",
        "Position": 152
    },
    {
        "SongID": 7086,
        "Title": "White Mustang",
        "Artist": "Lana Del Rey",
        "Position": 149
    },
    {
        "SongID": 9506,
        "Title": "Seven",
        "Artist": "Jung Kook",
        "Position": 18
    },
    {
        "SongID": 11932,
        "Title": "NIGHTS LIKE THIS",
        "Artist": "The Kid LAROI",
        "Position": 94
    },
    {
        "SongID": 12447,
        "Title": "Espresso",
        "Artist": "Sabrina Carpenter",
        "Position": 11
    },
    {
        "SongID": 12448,
        "Title": "MILLION DOLLAR BABY",
        "Artist": "Tommy Richman",
        "Position": 191
    },
    {
        "SongID": 12449,
        "Title": "LUNCH",
        "Artist": "Billie Eilish",
        "Position": 84
    },
    {
        "SongID": 12450,
        "Title": "Not Like Us",
        "Artist": "Kendrick Lamar",
        "Position": 31
    },
    {
        "SongID": 12451,
        "Title": "BIRDS OF A FEATHER",
        "Artist": "Billie Eilish",
        "Position": 2
    },
    {
        "SongID": 12453,
        "Title": "Too Sweet",
        "Artist": "Hozier",
        "Position": 171
    },
    {
        "SongID": 12454,
        "Title": "i like the way you kiss me",
        "Artist": "Artemas",
        "Position": 71
    },
    {
        "SongID": 12499,
        "Title": "CHIHIRO",
        "Artist": "Billie Eilish",
        "Position": 20
    },
    {
        "SongID": 12597,
        "Title": "we can't be friends (wait for your love)",
        "Artist": "Ariana Grande",
        "Position": 44
    },
    {
        "SongID": 12606,
        "Title": "End of Beginning",
        "Artist": "Djo",
        "Position": 22
    },
    {
        "SongID": 12959,
        "Title": "WILDFLOWER",
        "Artist": "Billie Eilish",
        "Position": 3
    },
    {
        "SongID": 13093,
        "Title": "BLUE",
        "Artist": "Billie Eilish",
        "Position": 119
    },
    {
        "SongID": 13521,
        "Title": "Good Luck, Babe!",
        "Artist": "Chappell Roan",
        "Position": 30
    },
    {
        "SongID": 13626,
        "Title": "L’AMOUR DE MA VIE",
        "Artist": "Billie Eilish",
        "Position": 140
    },
    {
        "SongID": 13822,
        "Title": "Type Shit",
        "Artist": "Future",
        "Position": 166
    },
    {
        "SongID": 18856,
        "Title": "If We Being Rëal",
        "Artist": "Yeat",
        "Position": 78
    },
    {
        "SongID": 22054,
        "Title": "Starboy",
        "Artist": "The Weeknd",
        "Position": 69
    },
    {
        "SongID": 33277,
        "Title": "FRI(END)S",
        "Artist": "V",
        "Position": 114
    },
    {
        "SongID": 43263,
        "Title": "All The Stars",
        "Artist": "Kendrick Lamar",
        "Position": 169
    },
    {
        "SongID": 106893,
        "Title": "Moonlight",
        "Artist": "XXXTENTACION",
        "Position": 160
    },
    {
        "SongID": 107276,
        "Title": "everything i wanted",
        "Artist": "Billie Eilish",
        "Position": 175
    },
    {
        "SongID": 110771,
        "Title": "Young And Beautiful",
        "Artist": "Lana Del Rey",
        "Position": 192
    },
    {
        "SongID": 113593,
        "Title": "Blinding Lights",
        "Artist": "The Weeknd",
        "Position": 164
    },
    {
        "SongID": 115648,
        "Title": "lovely",
        "Artist": "Billie Eilish",
        "Position": 128
    },
    {
        "SongID": 123212,
        "Title": "Falling Down - Bonus Track",
        "Artist": "Lil Peep",
        "Position": 139
    },
    {
        "SongID": 136741,
        "Title": "Khaleny Fe Hodnak",
        "Artist": "Tamer Ashour",
        "Position": 154
    },
    {
        "SongID": 136746,
        "Title": "Zrouf Mandany",
        "Artist": "Wael Jassar",
        "Position": 200
    },
    {
        "SongID": 165631,
        "Title": "Something About You",
        "Artist": "Eyedress",
        "Position": 105
    },
    {
        "SongID": 185372,
        "Title": "Walla Haram",
        "Artist": "Habeeb Ali",
        "Position": 198
    },
    {
        "SongID": 185389,
        "Title": "Duvet",
        "Artist": "bôa",
        "Position": 82
    },
    {
        "SongID": 185404,
        "Title": "Tejene (2)",
        "Artist": "Ayed",
        "Position": 132
    },
    {
        "SongID": 185438,
        "Title": "Rdy",
        "Artist": "Ayed",
        "Position": 59
    },
    {
        "SongID": 185489,
        "Title": "The Lost Soul Down X Lost Soul",
        "Artist": "NBSPLV",
        "Position": 142
    },
    {
        "SongID": 185600,
        "Title": "Be My First One",
        "Artist": "TalkinToys",
        "Position": 63
    },
    {
        "SongID": 185668,
        "Title": "Nadeit",
        "Artist": "Abass Ibrahim",
        "Position": 131
    },
    {
        "SongID": 201555,
        "Title": "SLAY!",
        "Artist": "Eternxlkz",
        "Position": 74
    },
    {
        "SongID": 202317,
        "Title": "FUNKED UP - SLOWED",
        "Artist": "xxanteria",
        "Position": 103
    },
    {
        "SongID": 202457,
        "Title": "MONTAGEM DIAMANTE ROSA - SLOWED",
        "Artist": "vtze archive",
        "Position": 112
    },
    {
        "SongID": 203167,
        "Title": "LET THE WORLD BURN",
        "Artist": "Chris Grey",
        "Position": 147
    },
    {
        "SongID": 212451,
        "Title": "كلام عينيه",
        "Artist": "Sherine",
        "Position": 137
    },
    {
        "SongID": 212453,
        "Title": "هيجيلي موجوع",
        "Artist": "Tamer Ashour",
        "Position": 68
    },
    {
        "SongID": 212462,
        "Title": "وغلاوتك",
        "Artist": "Amr Diab",
        "Position": 143
    },
    {
        "SongID": 212527,
        "Title": "هو انت مين",
        "Artist": "Angham",
        "Position": 104
    },
    {
        "SongID": 250829,
        "Title": "Akhsamna Tandas - Remix",
        "Artist": "Shela",
        "Position": 184
    },
    {
        "SongID": 250831,
        "Title": "يا ابن الأوادم",
        "Artist": "Abdul Majeed Abdullah",
        "Position": 122
    },
    {
        "SongID": 250835,
        "Title": "وين صرتي",
        "Artist": "Raad And Methaq",
        "Position": 95
    },
    {
        "SongID": 250846,
        "Title": "قلت مش هتسبني",
        "Artist": "Oumaima Taleb",
        "Position": 41
    },
    {
        "SongID": 250859,
        "Title": "هذا دمعك",
        "Artist": "Tayseer Al Safeer",
        "Position": 124
    },
    {
        "SongID": 250881,
        "Title": "المهزلة",
        "Artist": "Nasrat Al Bader",
        "Position": 45
    },
    {
        "SongID": 250883,
        "Title": "شلون بية",
        "Artist": "Aws Al Saber",
        "Position": 32
    },
    {
        "SongID": 250922,
        "Title": "عشت لحظات",
        "Artist": "Husam Al Rassam",
        "Position": 153
    },
    {
        "SongID": 250936,
        "Title": "مغربية طيارة",
        "Artist": "Astknan Maghribi",
        "Position": 25
    },
    {
        "SongID": 251026,
        "Title": "ويلاه",
        "Artist": "Rashed Al-Majed",
        "Position": 111
    },
    {
        "SongID": 251057,
        "Title": "ميت اني",
        "Artist": "Sabah Mahmod",
        "Position": 70
    },
    {
        "SongID": 251095,
        "Title": "Alam Aloshag",
        "Artist": "Khaled Almuthafar",
        "Position": 93
    },
    {
        "SongID": 251163,
        "Title": "I Bet on Losing Dogs",
        "Artist": "Mitski",
        "Position": 199
    },
    {
        "SongID": 251233,
        "Title": "Khayinah Wama Tansafi",
        "Artist": "Rabea",
        "Position": 158
    },
    {
        "SongID": 251268,
        "Title": "سعوديون",
        "Artist": "Ayed",
        "Position": 123
    },
    {
        "SongID": 309424,
        "Title": "Please Please Please",
        "Artist": "Sabrina Carpenter",
        "Position": 42
    },
    {
        "SongID": 501280,
        "Title": "Die With A Smile",
        "Artist": "Lady Gaga",
        "Position": 1
    },
    {
        "SongID": 501282,
        "Title": "Taste",
        "Artist": "Sabrina Carpenter",
        "Position": 29
    },
    {
        "SongID": 501283,
        "Title": "Who",
        "Artist": "Jimin",
        "Position": 13
    },
    {
        "SongID": 501290,
        "Title": "Bed Chem",
        "Artist": "Sabrina Carpenter",
        "Position": 145
    },
    {
        "SongID": 501295,
        "Title": "Big Dawgs",
        "Artist": "Hanumankind",
        "Position": 57
    },
    {
        "SongID": 501299,
        "Title": "Gata Only",
        "Artist": "FloyyMenor",
        "Position": 24
    },
    {
        "SongID": 501301,
        "Title": "Guess featuring Billie Eilish",
        "Artist": "Charli xcx",
        "Position": 75
    },
    {
        "SongID": 501313,
        "Title": "New Woman",
        "Artist": "LISA",
        "Position": 52
    },
    {
        "SongID": 501318,
        "Title": "Alibi",
        "Artist": "Sevdaliza",
        "Position": 51
    },
    {
        "SongID": 501325,
        "Title": "I Love You, I'm Sorry",
        "Artist": "Gracie Abrams",
        "Position": 67
    },
    {
        "SongID": 501328,
        "Title": "Sailor Song",
        "Artist": "Gigi Perez",
        "Position": 36
    },
    {
        "SongID": 501344,
        "Title": "Disco",
        "Artist": "Surf Curse",
        "Position": 159
    },
    {
        "SongID": 501359,
        "Title": "KEHLANI",
        "Artist": "Jordan Adetunji",
        "Position": 97
    },
    {
        "SongID": 501471,
        "Title": "Be Mine",
        "Artist": "Jimin",
        "Position": 85
    },
    {
        "SongID": 501803,
        "Title": "KEEP UP",
        "Artist": "Odetari",
        "Position": 15
    },
    {
        "SongID": 501965,
        "Title": "CRAZY",
        "Artist": "LE SSERAFIM",
        "Position": 118
    },
    {
        "SongID": 501979,
        "Title": "Touch",
        "Artist": "KATSEYE",
        "Position": 89
    },
    {
        "SongID": 502677,
        "Title": "Diet Pepsi",
        "Artist": "Addison Rae",
        "Position": 108
    },
    {
        "SongID": 502699,
        "Title": "Rockstar",
        "Artist": "LISA",
        "Position": 106
    },
    {
        "SongID": 503653,
        "Title": "Embrace It",
        "Artist": "Ndotz",
        "Position": 6
    },
    {
        "SongID": 504095,
        "Title": "NEW DROP",
        "Artist": "Don Toliver",
        "Position": 55
    },
    {
        "SongID": 504680,
        "Title": "Die For You",
        "Artist": "The Weeknd",
        "Position": 170
    },
    {
        "SongID": 504868,
        "Title": "TORE UP",
        "Artist": "Don Toliver",
        "Position": 115
    },
    {
        "SongID": 531835,
        "Title": "No One Noticed",
        "Artist": "The Marías",
        "Position": 7
    },
    {
        "SongID": 532459,
        "Title": "X-SLIDE",
        "Artist": "808iuli",
        "Position": 26
    },
    {
        "SongID": 532765,
        "Title": "Ela Joga na Hora",
        "Artist": "Mc Pogba",
        "Position": 163
    },
    {
        "SongID": 533606,
        "Title": "حبيبي ليه",
        "Artist": "TUL8TE",
        "Position": 107
    },
    {
        "SongID": 533620,
        "Title": "Ganeni",
        "Artist": "Elyanna",
        "Position": 156
    },
    {
        "SongID": 533855,
        "Title": "Did It First",
        "Artist": "Ice Spice",
        "Position": 181
    },
    {
        "SongID": 535607,
        "Title": "GLORY",
        "Artist": "Ogryzek",
        "Position": 35
    },
    {
        "SongID": 535608,
        "Title": "Se Paciente Funk",
        "Artist": "RD12",
        "Position": 178
    },
    {
        "SongID": 535660,
        "Title": "Slide da Treme Melódica v2",
        "Artist": "DJ FNK",
        "Position": 155
    },
    {
        "SongID": 537361,
        "Title": "ايباه (ريمكس)",
        "Artist": "Bee Remix",
        "Position": 4
    },
    {
        "SongID": 537362,
        "Title": "Lammah",
        "Artist": "Ayed",
        "Position": 5
    },
    {
        "SongID": 537363,
        "Title": "Aybaah",
        "Artist": "Saif Amer",
        "Position": 8
    },
    {
        "SongID": 537365,
        "Title": "حبيبي راح مسرع",
        "Artist": "Kstr",
        "Position": 17
    },
    {
        "SongID": 537370,
        "Title": "Al Masafa",
        "Artist": "Ayed",
        "Position": 48
    },
    {
        "SongID": 537373,
        "Title": "MONTAGEM VOZES PROFUNDAS - TikTok Version",
        "Artist": "DJ MAXZZ",
        "Position": 86
    },
    {
        "SongID": 537375,
        "Title": "مغربي صمخه",
        "Artist": "Maha",
        "Position": 96
    },
    {
        "SongID": 537380,
        "Title": "AURA",
        "Artist": "Ogryzek",
        "Position": 73
    },
    {
        "SongID": 537383,
        "Title": "Tari Alzaal",
        "Artist": "Aseel Hameem",
        "Position": 83
    },
    {
        "SongID": 537388,
        "Title": "NEXT!",
        "Artist": "NCTS",
        "Position": 121
    },
    {
        "SongID": 537390,
        "Title": "It's Going Down Now",
        "Artist": "Azumi Takahashi",
        "Position": 182
    },
    {
        "SongID": 537392,
        "Title": "Roi - Instrumental Slowed",
        "Artist": "Mckyyy",
        "Position": 77
    },
    {
        "SongID": 537397,
        "Title": "FUNK UNIVERSO",
        "Artist": "Irokz",
        "Position": 188
    },
    {
        "SongID": 537401,
        "Title": "welcome and goodbye",
        "Artist": "Dream, Ivory",
        "Position": 66
    },
    {
        "SongID": 537403,
        "Title": "Khber Fzzni",
        "Artist": "Nabel Al Adeeb",
        "Position": 116
    },
    {
        "SongID": 537411,
        "Title": "Beeper Funk - Slowed",
        "Artist": "DJ Paulinho Mondi Da Baixa Baviera",
        "Position": 134
    },
    {
        "SongID": 537424,
        "Title": "Hope",
        "Artist": "XXXTENTACION",
        "Position": 146
    },
    {
        "SongID": 538737,
        "Title": "Timeless",
        "Artist": "The Weeknd",
        "Position": 10
    },
    {
        "SongID": 538755,
        "Title": "FUNK DO BOUNCE (Slowed)",
        "Artist": "Ariis",
        "Position": 39
    },
    {
        "SongID": 538796,
        "Title": "Skyfall - Full Length",
        "Artist": "Adele",
        "Position": 50
    },
    {
        "SongID": 538895,
        "Title": "رحتي خنتيني وغدرتي وهانت العشره عليك - مسرع",
        "Artist": "umiy",
        "Position": 9
    },
    {
        "SongID": 538923,
        "Title": "Moonlit Floor",
        "Artist": "LISA",
        "Position": 43
    },
    {
        "SongID": 539130,
        "Title": "BRUXO FANTASMA - SUPER SLOWED",
        "Artist": "LXNGVX",
        "Position": 168
    },
    {
        "SongID": 539332,
        "Title": "يما كضومي",
        "Artist": "SixFourNine",
        "Position": 138
    },
    {
        "SongID": 800037,
        "Title": "شدي ولدك",
        "Artist": "Astknan Maghribi",
        "Position": 38
    },
    {
        "SongID": 800108,
        "Title": "ماتيجي اعدي عليكي",
        "Artist": "TUL8TE",
        "Position": 109
    },
    {
        "SongID": 800112,
        "Title": "ويلي",
        "Artist": "Nasrat Al Bader",
        "Position": 113
    },
    {
        "SongID": 800132,
        "Title": "ياما حاولت",
        "Artist": "Abdul Majeed Abdullah",
        "Position": 133
    },
    {
        "SongID": 800150,
        "Title": "الله يعوض علي",
        "Artist": "عايل",
        "Position": 151
    },
    {
        "SongID": 800179,
        "Title": "مهموم",
        "Artist": "Raad And Methaq",
        "Position": 180
    },
    {
        "SongID": 800188,
        "Title": "الناس انواع",
        "Artist": "احميده البرهومي",
        "Position": 189
    }
]