[
    {
        "SongID": 1,
        "Title": "Cruel Summer",
        "Artist": "Taylor Swift",
        "Position": 19
    },
    {
        "SongID": 6,
        "Title": "One Of The Girls",
        "Artist": "The Weeknd",
        "Position": 27
    },
    {
        "SongID": 7,
        "Title": "What Was I Made For? [From The Motion Picture \"Barbie\"]",
        "Artist": "Billie Eilish",
        "Position": 184
    },
    {
        "SongID": 8,
        "Title": "Standing Next to You",
        "Artist": "Jung Kook",
        "Position": 115
    },
    {
        "SongID": 23,
        "Title": "Flowers",
        "Artist": "Miley Cyrus",
        "Position": 148
    },
    {
        "SongID": 25,
        "Title": "Love Me Again",
        "Artist": "V",
        "Position": 54
    },
    {
        "SongID": 27,
        "Title": "Beautiful Things",
        "Artist": "Benson Boone",
        "Position": 34
    },
    {
        "SongID": 35,
        "Title": "Super Shy",
        "Artist": "NewJeans",
        "Position": 168
    },
    {
        "SongID": 37,
        "Title": "I Wanna Be Yours",
        "Artist": "Arctic Monkeys",
        "Position": 60
    },
    {
        "SongID": 46,
        "Title": "FE!N",
        "Artist": "Travis Scott",
        "Position": 50
    },
    {
        "SongID": 51,
        "Title": "As It Was",
        "Artist": "Harry Styles",
        "Position": 163
    },
    {
        "SongID": 53,
        "Title": "Kill Bill",
        "Artist": "SZA",
        "Position": 32
    },
    {
        "SongID": 61,
        "Title": "Yellow",
        "Artist": "Coldplay",
        "Position": 76
    },
    {
        "SongID": 64,
        "Title": "Sweater Weather",
        "Artist": "The Neighbourhood",
        "Position": 64
    },
    {
        "SongID": 68,
        "Title": "Lover",
        "Artist": "Taylor Swift",
        "Position": 182
    },
    {
        "SongID": 73,
        "Title": "Perfect Night",
        "Artist": "LE SSERAFIM",
        "Position": 130
    },
    {
        "SongID": 81,
        "Title": "Snooze",
        "Artist": "SZA",
        "Position": 79
    },
    {
        "SongID": 82,
        "Title": "Here With Me",
        "Artist": "d4vd",
        "Position": 81
    },
    {
        "SongID": 94,
        "Title": "vampire",
        "Artist": "Olivia Rodrigo",
        "Position": 73
    },
    {
        "SongID": 101,
        "Title": "My Love Mine All Mine",
        "Artist": "Mitski",
        "Position": 44
    },
    {
        "SongID": 103,
        "Title": "Pink + White",
        "Artist": "Frank Ocean",
        "Position": 195
    },
    {
        "SongID": 106,
        "Title": "Perfect",
        "Artist": "Ed Sheeran",
        "Position": 91
    },
    {
        "SongID": 108,
        "Title": "Someone You Loved",
        "Artist": "Lewis Capaldi",
        "Position": 63
    },
    {
        "SongID": 121,
        "Title": "Romantic Homicide",
        "Artist": "d4vd",
        "Position": 196
    },
    {
        "SongID": 123,
        "Title": "Nonsense",
        "Artist": "Sabrina Carpenter",
        "Position": 31
    },
    {
        "SongID": 141,
        "Title": "Locked out of Heaven",
        "Artist": "Bruno Mars",
        "Position": 189
    },
    {
        "SongID": 145,
        "Title": "exes",
        "Artist": "Tate McRae",
        "Position": 128
    },
    {
        "SongID": 150,
        "Title": "When I Was Your Man",
        "Artist": "Bruno Mars",
        "Position": 101
    },
    {
        "SongID": 152,
        "Title": "Night Changes",
        "Artist": "One Direction",
        "Position": 43
    },
    {
        "SongID": 154,
        "Title": "That's What I Like",
        "Artist": "Bruno Mars",
        "Position": 180
    },
    {
        "SongID": 155,
        "Title": "Shape of You",
        "Artist": "Ed Sheeran",
        "Position": 150
    },
    {
        "SongID": 175,
        "Title": "OMG",
        "Artist": "NewJeans",
        "Position": 199
    },
    {
        "SongID": 181,
        "Title": "ETA",
        "Artist": "NewJeans",
        "Position": 70
    },
    {
        "SongID": 196,
        "Title": "Dandelions",
        "Artist": "Ruth B.",
        "Position": 52
    },
    {
        "SongID": 201,
        "Title": "Viva La Vida",
        "Artist": "Coldplay",
        "Position": 41
    },
    {
        "SongID": 204,
        "Title": "we fell in love in october",
        "Artist": "girl in red",
        "Position": 89
    },
    {
        "SongID": 205,
        "Title": "Apocalypse",
        "Artist": "Cigarettes After Sex",
        "Position": 68
    },
    {
        "SongID": 208,
        "Title": "Sparks",
        "Artist": "Coldplay",
        "Position": 188
    },
    {
        "SongID": 209,
        "Title": "traitor",
        "Artist": "Olivia Rodrigo",
        "Position": 136
    },
    {
        "SongID": 210,
        "Title": "drivers license",
        "Artist": "Olivia Rodrigo",
        "Position": 112
    },
    {
        "SongID": 211,
        "Title": "deja vu",
        "Artist": "Olivia Rodrigo",
        "Position": 110
    },
    {
        "SongID": 216,
        "Title": "Counting Stars",
        "Artist": "OneRepublic",
        "Position": 127
    },
    {
        "SongID": 229,
        "Title": "Drama",
        "Artist": "aespa",
        "Position": 134
    },
    {
        "SongID": 232,
        "Title": "Let Me Down Slowly",
        "Artist": "Alec Benjamin",
        "Position": 187
    },
    {
        "SongID": 245,
        "Title": "I Love You So",
        "Artist": "The Walters",
        "Position": 57
    },
    {
        "SongID": 246,
        "Title": "In The Stars",
        "Artist": "Benson Boone",
        "Position": 99
    },
    {
        "SongID": 272,
        "Title": "From The Start",
        "Artist": "Laufey",
        "Position": 121
    },
    {
        "SongID": 274,
        "Title": "Numb",
        "Artist": "Linkin Park",
        "Position": 156
    },
    {
        "SongID": 277,
        "Title": "Somewhere Only We Know",
        "Artist": "Keane",
        "Position": 174
    },
    {
        "SongID": 284,
        "Title": "A Sky Full of Stars",
        "Artist": "Coldplay",
        "Position": 82
    },
    {
        "SongID": 288,
        "Title": "Cry",
        "Artist": "Cigarettes After Sex",
        "Position": 179
    },
    {
        "SongID": 292,
        "Title": "Demons",
        "Artist": "Imagine Dragons",
        "Position": 131
    },
    {
        "SongID": 297,
        "Title": "Photograph",
        "Artist": "Ed Sheeran",
        "Position": 93
    },
    {
        "SongID": 301,
        "Title": "The Night We Met",
        "Artist": "Lord Huron",
        "Position": 133
    },
    {
        "SongID": 371,
        "Title": "Just the Way You Are",
        "Artist": "Bruno Mars",
        "Position": 66
    },
    {
        "SongID": 376,
        "Title": "you broke me first",
        "Artist": "Tate McRae",
        "Position": 183
    },
    {
        "SongID": 395,
        "Title": "Maps",
        "Artist": "Maroon 5",
        "Position": 178
    },
    {
        "SongID": 398,
        "Title": "Closer",
        "Artist": "The Chainsmokers",
        "Position": 161
    },
    {
        "SongID": 451,
        "Title": "Sunroof",
        "Artist": "Nicky Youre",
        "Position": 92
    },
    {
        "SongID": 456,
        "Title": "Ditto",
        "Artist": "NewJeans",
        "Position": 190
    },
    {
        "SongID": 528,
        "Title": "Payphone",
        "Artist": "Maroon 5",
        "Position": 118
    },
    {
        "SongID": 537,
        "Title": "One Last Time",
        "Artist": "Ariana Grande",
        "Position": 157
    },
    {
        "SongID": 557,
        "Title": "I Want It That Way",
        "Artist": "Backstreet Boys",
        "Position": 164
    },
    {
        "SongID": 575,
        "Title": "Sweet but Psycho",
        "Artist": "Ava Max",
        "Position": 169
    },
    {
        "SongID": 577,
        "Title": "We Don't Talk Anymore",
        "Artist": "Charlie Puth",
        "Position": 62
    },
    {
        "SongID": 608,
        "Title": "Glimpse of Us",
        "Artist": "Joji",
        "Position": 173
    },
    {
        "SongID": 720,
        "Title": "I Like Me Better",
        "Artist": "Lauv",
        "Position": 177
    },
    {
        "SongID": 793,
        "Title": "Easy On Me",
        "Artist": "Adele",
        "Position": 176
    },
    {
        "SongID": 799,
        "Title": "Nobody Gets Me",
        "Artist": "SZA",
        "Position": 104
    },
    {
        "SongID": 845,
        "Title": "seasons",
        "Artist": "wave to earth",
        "Position": 144
    },
    {
        "SongID": 906,
        "Title": "Hall of Fame",
        "Artist": "The Script",
        "Position": 106
    },
    {
        "SongID": 963,
        "Title": "double take",
        "Artist": "Dhruv",
        "Position": 23
    },
    {
        "SongID": 1154,
        "Title": "3D",
        "Artist": "Jung Kook",
        "Position": 122
    },
    {
        "SongID": 1257,
        "Title": "drunk text",
        "Artist": "Henry Moodie",
        "Position": 87
    },
    {
        "SongID": 1369,
        "Title": "Unstoppable",
        "Artist": "Sia",
        "Position": 193
    },
    {
        "SongID": 1460,
        "Title": "Feather",
        "Artist": "Sabrina Carpenter",
        "Position": 86
    },
    {
        "SongID": 1934,
        "Title": "Symphony",
        "Artist": "Clean Bandit",
        "Position": 147
    },
    {
        "SongID": 1981,
        "Title": "It Will Rain",
        "Artist": "Bruno Mars",
        "Position": 88
    },
    {
        "SongID": 2078,
        "Title": "Tip Toe",
        "Artist": "HYBS",
        "Position": 191
    },
    {
        "SongID": 2088,
        "Title": "24/7, 365",
        "Artist": "elijah woods",
        "Position": 105
    },
    {
        "SongID": 2264,
        "Title": "greedy",
        "Artist": "Tate McRae",
        "Position": 39
    },
    {
        "SongID": 2670,
        "Title": "Lose Control",
        "Artist": "Teddy Swims",
        "Position": 137
    },
    {
        "SongID": 3005,
        "Title": "字字句句",
        "Artist": "卢卢快闭嘴",
        "Position": 47
    },
    {
        "SongID": 3960,
        "Title": "The Man Who Can't Be Moved",
        "Artist": "The Script",
        "Position": 154
    },
    {
        "SongID": 4402,
        "Title": "Bye Bye Bye",
        "Artist": "*NSYNC",
        "Position": 36
    },
    {
        "SongID": 6571,
        "Title": "我会等",
        "Artist": "承桓",
        "Position": 49
    },
    {
        "SongID": 9506,
        "Title": "Seven",
        "Artist": "Jung Kook",
        "Position": 17
    },
    {
        "SongID": 10345,
        "Title": "如果可以 - 電影\"月老\"主題曲",
        "Artist": "WeiBird",
        "Position": 75
    },
    {
        "SongID": 11427,
        "Title": "从前说",
        "Artist": "小阿七",
        "Position": 71
    },
    {
        "SongID": 11932,
        "Title": "NIGHTS LIKE THIS",
        "Artist": "The Kid LAROI",
        "Position": 67
    },
    {
        "SongID": 12447,
        "Title": "Espresso",
        "Artist": "Sabrina Carpenter",
        "Position": 5
    },
    {
        "SongID": 12448,
        "Title": "MILLION DOLLAR BABY",
        "Artist": "Tommy Richman",
        "Position": 46
    },
    {
        "SongID": 12450,
        "Title": "Not Like Us",
        "Artist": "Kendrick Lamar",
        "Position": 125
    },
    {
        "SongID": 12451,
        "Title": "BIRDS OF A FEATHER",
        "Artist": "Billie Eilish",
        "Position": 3
    },
    {
        "SongID": 12453,
        "Title": "Too Sweet",
        "Artist": "Hozier",
        "Position": 22
    },
    {
        "SongID": 12454,
        "Title": "i like the way you kiss me",
        "Artist": "Artemas",
        "Position": 145
    },
    {
        "SongID": 12534,
        "Title": "怎麼了",
        "Artist": "Eric Chou",
        "Position": 146
    },
    {
        "SongID": 12536,
        "Title": "摯友",
        "Artist": "Eric Chou",
        "Position": 172
    },
    {
        "SongID": 12597,
        "Title": "we can't be friends (wait for your love)",
        "Artist": "Ariana Grande",
        "Position": 14
    },
    {
        "SongID": 12604,
        "Title": "Fortnight",
        "Artist": "Taylor Swift",
        "Position": 45
    },
    {
        "SongID": 12606,
        "Title": "End of Beginning",
        "Artist": "Djo",
        "Position": 29
    },
    {
        "SongID": 12715,
        "Title": "Stargazing",
        "Artist": "Myles Smith",
        "Position": 83
    },
    {
        "SongID": 12959,
        "Title": "WILDFLOWER",
        "Artist": "Billie Eilish",
        "Position": 20
    },
    {
        "SongID": 13137,
        "Title": "I Can Do It With a Broken Heart",
        "Artist": "Taylor Swift",
        "Position": 96
    },
    {
        "SongID": 13481,
        "Title": "Slow It Down",
        "Artist": "Benson Boone",
        "Position": 84
    },
    {
        "SongID": 13482,
        "Title": "Saturn",
        "Artist": "SZA",
        "Position": 56
    },
    {
        "SongID": 13521,
        "Title": "Good Luck, Babe!",
        "Artist": "Chappell Roan",
        "Position": 6
    },
    {
        "SongID": 13630,
        "Title": "Magnetic",
        "Artist": "ILLIT",
        "Position": 24
    },
    {
        "SongID": 13632,
        "Title": "See You Again",
        "Artist": "Tyler, The Creator",
        "Position": 109
    },
    {
        "SongID": 13633,
        "Title": "Supernova",
        "Artist": "aespa",
        "Position": 53
    },
    {
        "SongID": 13738,
        "Title": "有些",
        "Artist": "颜人中",
        "Position": 170
    },
    {
        "SongID": 13739,
        "Title": "晴天",
        "Artist": "Jay Chou",
        "Position": 124
    },
    {
        "SongID": 13917,
        "Title": "擱淺",
        "Artist": "Jay Chou",
        "Position": 129
    },
    {
        "SongID": 14774,
        "Title": "I Ain't Worried",
        "Artist": "OneRepublic",
        "Position": 155
    },
    {
        "SongID": 14870,
        "Title": "I Don't Wanna Wait",
        "Artist": "David Guetta",
        "Position": 119
    },
    {
        "SongID": 17596,
        "Title": "Shivers",
        "Artist": "Ed Sheeran",
        "Position": 153
    },
    {
        "SongID": 19731,
        "Title": "在加納共和國離婚",
        "Artist": "Firdhaus",
        "Position": 30
    },
    {
        "SongID": 22054,
        "Title": "Starboy",
        "Artist": "The Weeknd",
        "Position": 167
    },
    {
        "SongID": 33273,
        "Title": "How Sweet",
        "Artist": "NewJeans",
        "Position": 160
    },
    {
        "SongID": 33275,
        "Title": "Armageddon",
        "Artist": "aespa",
        "Position": 74
    },
    {
        "SongID": 33284,
        "Title": "SHEESH",
        "Artist": "BABYMONSTER",
        "Position": 143
    },
    {
        "SongID": 34969,
        "Title": "intro (end of the world)",
        "Artist": "Ariana Grande",
        "Position": 80
    },
    {
        "SongID": 38590,
        "Title": "Smart",
        "Artist": "LE SSERAFIM",
        "Position": 138
    },
    {
        "SongID": 43263,
        "Title": "All The Stars",
        "Artist": "Kendrick Lamar",
        "Position": 192
    },
    {
        "SongID": 49439,
        "Title": "这是你期盼的长大吗",
        "Artist": "ZQS",
        "Position": 103
    },
    {
        "SongID": 49440,
        "Title": "总会有人 (男版)",
        "Artist": "承桓",
        "Position": 55
    },
    {
        "SongID": 49443,
        "Title": "友谊长存",
        "Artist": "Firdhaus",
        "Position": 90
    },
    {
        "SongID": 85546,
        "Title": "Say You Won't Let Go",
        "Artist": "James Arthur",
        "Position": 142
    },
    {
        "SongID": 111217,
        "Title": "Talking to the Moon",
        "Artist": "Bruno Mars",
        "Position": 175
    },
    {
        "SongID": 114692,
        "Title": "Ghost",
        "Artist": "Justin Bieber",
        "Position": 38
    },
    {
        "SongID": 120025,
        "Title": "說好不哭",
        "Artist": "Jay Chou",
        "Position": 123
    },
    {
        "SongID": 123550,
        "Title": "the boy is mine",
        "Artist": "Ariana Grande",
        "Position": 171
    },
    {
        "SongID": 130770,
        "Title": "Best Part",
        "Artist": "H.E.R.",
        "Position": 100
    },
    {
        "SongID": 130794,
        "Title": "Iris",
        "Artist": "The Goo Goo Dolls",
        "Position": 140
    },
    {
        "SongID": 130843,
        "Title": "HOT TO GO!",
        "Artist": "Chappell Roan",
        "Position": 85
    },
    {
        "SongID": 158903,
        "Title": "About You",
        "Artist": "The 1975",
        "Position": 126
    },
    {
        "SongID": 198448,
        "Title": "I miss you, I’m sorry",
        "Artist": "Gracie Abrams",
        "Position": 135
    },
    {
        "SongID": 223327,
        "Title": "告白氣球",
        "Artist": "Jay Chou",
        "Position": 94
    },
    {
        "SongID": 223335,
        "Title": "你,好不好? - TVBS連續劇【遺憾拼圖】片尾曲",
        "Artist": "Eric Chou",
        "Position": 97
    },
    {
        "SongID": 223377,
        "Title": "飞鸟和蝉",
        "Artist": "Ren Ran",
        "Position": 197
    },
    {
        "SongID": 223407,
        "Title": "可惜沒如果",
        "Artist": "JJ Lin",
        "Position": 166
    },
    {
        "SongID": 223605,
        "Title": "珊瑚海",
        "Artist": "Jay Chou",
        "Position": 200
    },
    {
        "SongID": 238319,
        "Title": "哪里都是你",
        "Artist": "隊長",
        "Position": 69
    },
    {
        "SongID": 238342,
        "Title": "你的答案",
        "Artist": "阿冗",
        "Position": 139
    },
    {
        "SongID": 238382,
        "Title": "love.",
        "Artist": "wave to earth",
        "Position": 198
    },
    {
        "SongID": 238385,
        "Title": "嚣张",
        "Artist": "en",
        "Position": 152
    },
    {
        "SongID": 251769,
        "Title": "感谢你曾来过",
        "Artist": "阿涵",
        "Position": 162
    },
    {
        "SongID": 251771,
        "Title": "我走后 - 发行版",
        "Artist": "小咪",
        "Position": 165
    },
    {
        "SongID": 251804,
        "Title": "爱怎么了",
        "Artist": "陈村长",
        "Position": 113
    },
    {
        "SongID": 251818,
        "Title": "若月亮没来（若是月亮还没来）",
        "Artist": "王宇宙Leto",
        "Position": 185
    },
    {
        "SongID": 260909,
        "Title": "最后一页 - Live",
        "Artist": "王赫野",
        "Position": 149
    },
    {
        "SongID": 309424,
        "Title": "Please Please Please",
        "Artist": "Sabrina Carpenter",
        "Position": 10
    },
    {
        "SongID": 309432,
        "Title": "Close To You",
        "Artist": "Gracie Abrams",
        "Position": 116
    },
    {
        "SongID": 501280,
        "Title": "Die With A Smile",
        "Artist": "Lady Gaga",
        "Position": 2
    },
    {
        "SongID": 501282,
        "Title": "Taste",
        "Artist": "Sabrina Carpenter",
        "Position": 4
    },
    {
        "SongID": 501283,
        "Title": "Who",
        "Artist": "Jimin",
        "Position": 1
    },
    {
        "SongID": 501288,
        "Title": "The Emptiness Machine",
        "Artist": "Linkin Park",
        "Position": 58
    },
    {
        "SongID": 501290,
        "Title": "Bed Chem",
        "Artist": "Sabrina Carpenter",
        "Position": 12
    },
    {
        "SongID": 501293,
        "Title": "Neva Play",
        "Artist": "Megan Thee Stallion",
        "Position": 194
    },
    {
        "SongID": 501295,
        "Title": "Big Dawgs",
        "Artist": "Hanumankind",
        "Position": 72
    },
    {
        "SongID": 501301,
        "Title": "Guess featuring Billie Eilish",
        "Artist": "Charli xcx",
        "Position": 114
    },
    {
        "SongID": 501313,
        "Title": "New Woman",
        "Artist": "LISA",
        "Position": 40
    },
    {
        "SongID": 501318,
        "Title": "Alibi",
        "Artist": "Sevdaliza",
        "Position": 61
    },
    {
        "SongID": 501322,
        "Title": "Good Graces",
        "Artist": "Sabrina Carpenter",
        "Position": 33
    },
    {
        "SongID": 501325,
        "Title": "I Love You, I'm Sorry",
        "Artist": "Gracie Abrams",
        "Position": 13
    },
    {
        "SongID": 501328,
        "Title": "Sailor Song",
        "Artist": "Gigi Perez",
        "Position": 15
    },
    {
        "SongID": 501338,
        "Title": "Juno",
        "Artist": "Sabrina Carpenter",
        "Position": 26
    },
    {
        "SongID": 501348,
        "Title": "Apple",
        "Artist": "Charli xcx",
        "Position": 120
    },
    {
        "SongID": 501471,
        "Title": "Be Mine",
        "Artist": "Jimin",
        "Position": 25
    },
    {
        "SongID": 501803,
        "Title": "KEEP UP",
        "Artist": "Odetari",
        "Position": 108
    },
    {
        "SongID": 501965,
        "Title": "CRAZY",
        "Artist": "LE SSERAFIM",
        "Position": 21
    },
    {
        "SongID": 501979,
        "Title": "Touch",
        "Artist": "KATSEYE",
        "Position": 8
    },
    {
        "SongID": 502085,
        "Title": "Something Just Like This",
        "Artist": "The Chainsmokers",
        "Position": 37
    },
    {
        "SongID": 502303,
        "Title": "Supernatural",
        "Artist": "NewJeans",
        "Position": 159
    },
    {
        "SongID": 502311,
        "Title": "MEOW",
        "Artist": "MEOVV",
        "Position": 95
    },
    {
        "SongID": 502316,
        "Title": "Sticky",
        "Artist": "KISS OF LIFE",
        "Position": 181
    },
    {
        "SongID": 502426,
        "Title": "Mamushi",
        "Artist": "Megan Thee Stallion",
        "Position": 98
    },
    {
        "SongID": 502475,
        "Title": "BABY I'M BACK",
        "Artist": "The Kid LAROI",
        "Position": 35
    },
    {
        "SongID": 502677,
        "Title": "Diet Pepsi",
        "Artist": "Addison Rae",
        "Position": 9
    },
    {
        "SongID": 502678,
        "Title": "Stay",
        "Artist": "The Kid LAROI",
        "Position": 42
    },
    {
        "SongID": 502681,
        "Title": "能遇見，就很不錯了",
        "Artist": "Firdhaus",
        "Position": 48
    },
    {
        "SongID": 502699,
        "Title": "Rockstar",
        "Artist": "LISA",
        "Position": 78
    },
    {
        "SongID": 502791,
        "Title": "FOREVER",
        "Artist": "BABYMONSTER",
        "Position": 102
    },
    {
        "SongID": 503594,
        "Title": "Dancing In The Flames",
        "Artist": "The Weeknd",
        "Position": 51
    },
    {
        "SongID": 503616,
        "Title": "It's ok I'm ok",
        "Artist": "Tate McRae",
        "Position": 28
    },
    {
        "SongID": 503653,
        "Title": "Embrace It",
        "Artist": "Ndotz",
        "Position": 59
    },
    {
        "SongID": 504901,
        "Title": "Soft Spot",
        "Artist": "keshi",
        "Position": 11
    },
    {
        "SongID": 504902,
        "Title": "the cutest pair",
        "Artist": "Regina Song",
        "Position": 7
    },
    {
        "SongID": 504908,
        "Title": "Say",
        "Artist": "keshi",
        "Position": 141
    },
    {
        "SongID": 531739,
        "Title": "Heavy Is the Crown",
        "Artist": "Linkin Park",
        "Position": 111
    },
    {
        "SongID": 532448,
        "Title": "Chk Chk Boom",
        "Artist": "Stray Kids",
        "Position": 77
    },
    {
        "SongID": 534385,
        "Title": "GGUM",
        "Artist": "YEONJUN",
        "Position": 117
    },
    {
        "SongID": 537446,
        "Title": "1-800-hot-n-fun",
        "Artist": "LE SSERAFIM",
        "Position": 107
    },
    {
        "SongID": 537448,
        "Title": "如果爱忘了 - Live",
        "Artist": "Silence Wang",
        "Position": 65
    },
    {
        "SongID": 537451,
        "Title": "Debut",
        "Artist": "KATSEYE",
        "Position": 158
    },
    {
        "SongID": 537454,
        "Title": "嘉賓",
        "Artist": "张远",
        "Position": 132
    },
    {
        "SongID": 538737,
        "Title": "Timeless",
        "Artist": "The Weeknd",
        "Position": 18
    },
    {
        "SongID": 538923,
        "Title": "Moonlit Floor",
        "Artist": "LISA",
        "Position": 16
    },
    {
        "SongID": 538936,
        "Title": "Thick Of It",
        "Artist": "KSI",
        "Position": 151
    },
    {
        "SongID": 539049,
        "Title": "オトノケ - Otonoke",
        "Artist": "Creepy Nuts",
        "Position": 186
    }
]